HD/HDDMA.py
HD/HDHOOK.py
HD/HDIP.py
HD/HDJSON.py
HD/HDLUA.py
HD/HDNT.py
HD/HDPOCR.py
HD/HDVM.py
HD/HDVNC.py
HD/HDVT.py
HD/HDYOLOV.py
HD/HD主板机.py
HD/HD优化.py
HD/HD内存.py
HD/HD内置浏览器.py
HD/HD回调函数.py
HD/HD多线程.py
HD/HD实时绘制.py
HD/HD截图.py
HD/HD扩展.py
HD/HD插件.py
HD/HD智能识图.py
HD/HD汇编.py
HD/HD注入.py
HD/HD状态机.py
HD/HD环境.py
HD/HD登录.py
HD/HD盾.py
HD/HD窗口.py
HD/HD系统.py
HD/HD结构体.py
HD/HD识图.py
HD/HD识字.py
HD/HD调试.py
HD/HD资源.py
HD/HD返回值.py
HD/HD通用.py
HD/HD通讯.py
HD/HD键鼠.py
HD/HD驱动.py
HD/HD黑屏.py
HD/__init__.py
HD/config.py
hdgdk-2025.9.900.dist-info/METADATA
hdgdk-2025.9.900.dist-info/WHEEL
hdgdk-2025.9.900.dist-info/top_level.txt
hdgdk-2025.9.900.dist-info/RECORD
