Metadata-Version: 2.4
Name: hdgdk
Version: 2025.9.900
Summary: HD引擎Python调用模块
Home-page: https://github.com/zhangsan-ai/hd-python
Author: zhangsan
Author-email: 3258856837@qq.com
Maintainer: zhangsan
Maintainer-email: 3258856837@qq.com
License: MIT
Requires-Python: >=3.6
Dynamic: author
Dynamic: author-email
Dynamic: description
Dynamic: description-content-type
Dynamic: home-page
Dynamic: license
Dynamic: maintainer
Dynamic: maintainer-email
Dynamic: requires-python
Dynamic: summary
